jellystocks/__init__.py
jellystocks/cost_functions.py
jellystocks/data_downloader.py
jellystocks/jellyfish_search.py
jellystocks/main.py
jellystocks/portfolio.py
jellystocks/utils.py
JellyStocks-1.0.5.dist-info/LICENSE
JellyStocks-1.0.5.dist-info/METADATA
JellyStocks-1.0.5.dist-info/WHEEL
JellyStocks-1.0.5.dist-info/top_level.txt
JellyStocks-1.0.5.dist-info/RECORD
