Metadata-Version: 2.1
Name: JellyStocks
Version: 1.0.5
Summary: A Python library for optimizing stock portfolios using the Jellyfish Search optimization algorithm.
Author: Paul Barros Bessone
Author-email: paulbessone@gmail.co
License: BSD-2-Clause
License-File: LICENSE
Requires-Dist: setuptools (~=65.6.3)
Requires-Dist: pandas (~=1.5.3)
Requires-Dist: numpy (~=1.23.5)
Requires-Dist: tabulate (~=0.8.10)
Requires-Dist: yfinance (~=0.2.30)
Requires-Dist: tqdm (~=4.64.1)
